MANIFEST.in
README.md
setup.py
referer_parser/__init__.py
referer_parser.egg-info/PKG-INFO
referer_parser.egg-info/SOURCES.txt
referer_parser.egg-info/dependency_links.txt
referer_parser.egg-info/not-zip-safe
referer_parser.egg-info/top_level.txt
referer_parser/data/referers.json
referer_parser/test/__init__.py